django_gmzoom_tools/__init__.py
django_gmzoom_tools-0.1.2.dist-info/WHEEL
django_gmzoom_tools-0.1.2.dist-info/METADATA
django_gmzoom_tools-0.1.2.dist-info/RECORD
